trops/__init__.py
trops/capcmd.py
trops/env.py
trops/exec.py
trops/file.py
trops/init.py
trops/log.py
trops/release.py
trops/repo.py
trops/tablog.py
trops/tldr.py
trops/trops.py
trops/utils.py
trops/view.py
trops-0.2.34.dist-info/LICENSE
trops-0.2.34.dist-info/METADATA
trops-0.2.34.dist-info/WHEEL
trops-0.2.34.dist-info/entry_points.txt
trops-0.2.34.dist-info/RECORD
