Metadata-Version: 2.3
Name: trops
Version: 0.2.34
Summary: Track operations of distributed Linux systems
License: MIT
Author: Koji Tanaka
Author-email: kojiwelly@gmail.com
Requires-Python: >=3.8,<4.0
Classifier: License :: OSI Approved :: MIT License
Classifier: Programming Language :: Python :: 3
Classifier: Programming Language :: Python :: 3.8
Classifier: Programming Language :: Python :: 3.9
Classifier: Programming Language :: Python :: 3.10
Classifier: Programming Language :: Python :: 3.11
Classifier: Programming Language :: Python :: 3.12
Classifier: Programming Language :: Python :: 3.13
Requires-Dist: tabulate (>=0.8.10,<0.9.0)
